{
  "slug": "aboriginal-77f8735d",
  "parser_version": "moex_license_v1.0",
  "parsed_at": "2026-04-25T12:37:39+00:00",
  "paper_count": 3,
  "paper_with_questions": 3,
  "question_count": 12,
  "type_counts": {
    "essay": 12
  },
  "papers": [
    {
      "year": "114",
      "exam_code": "114140",
      "c": "511",
      "s": "2003",
      "q": "1",
      "subject": "衛生法規與倫理",
      "exam_name": "114年公務人員特種考試外交領事人員及外交行政人員考試、國際經濟商務人員考試、民航人員考試、原住民族考試",
      "q_pdf_exists": true,
      "a_pdf_exists": false,
      "corr_pdf_exists": false,
      "q_pdf_sha1": "790637ccbf11",
      "a_pdf_sha1": null,
      "format_detected": "pure_essay",
      "raw_question_count": 4,
      "answer_qnums_extracted": 0,
      "answer_corrections": 0,
      "is_correction_pdf_used": false,
      "status": "ok",
      "question_count": 4,
      "skipped_count": 0
    },
    {
      "year": "114",
      "exam_code": "114140",
      "c": "511",
      "s": "2002",
      "q": "1",
      "subject": "衛生行政",
      "exam_name": "114年公務人員特種考試外交領事人員及外交行政人員考試、國際經濟商務人員考試、民航人員考試、原住民族考試",
      "q_pdf_exists": true,
      "a_pdf_exists": false,
      "corr_pdf_exists": false,
      "q_pdf_sha1": "a4da5f4bf3a7",
      "a_pdf_sha1": null,
      "format_detected": "pure_essay",
      "raw_question_count": 4,
      "answer_qnums_extracted": 0,
      "answer_corrections": 0,
      "is_correction_pdf_used": false,
      "status": "ok",
      "question_count": 4,
      "skipped_count": 0
    },
    {
      "year": "114",
      "exam_code": "114140",
      "c": "511",
      "s": "2001",
      "q": "1",
      "subject": "醫療制度與品質管理",
      "exam_name": "114年公務人員特種考試外交領事人員及外交行政人員考試、國際經濟商務人員考試、民航人員考試、原住民族考試",
      "q_pdf_exists": true,
      "a_pdf_exists": false,
      "corr_pdf_exists": false,
      "q_pdf_sha1": "b2df7335229f",
      "a_pdf_sha1": null,
      "format_detected": "pure_essay",
      "raw_question_count": 4,
      "answer_qnums_extracted": 0,
      "answer_corrections": 0,
      "is_correction_pdf_used": false,
      "status": "ok",
      "question_count": 4,
      "skipped_count": 0
    }
  ],
  "questions": [
    {
      "id": "aboriginal-77f8735d-0001",
      "exam_id": "aboriginal-77f8735d",
      "question_type": "essay",
      "question": "請說明醫療法所稱主管機關為何？另說明該主管機關設計的特性，並進\n一步以管理功能分析優缺點。（25 分）",
      "options": [],
      "correct_answer": 0,
      "correct_answer_json": null,
      "auto_gradable": false,
      "explanation": null,
      "source_meta": {
        "parser_version": "moex_license_v1.0",
        "parsed_at": "2026-04-25T12:37:39+00:00",
        "source_pdf_sha1": "790637ccbf11",
        "answer_pdf_sha1": null,
        "source_family": "moex-gov-tw",
        "moex": {
          "exam_code": "114140",
          "c": "511",
          "s": "2003",
          "q": "1"
        },
        "raw_section_label": "甲、申論題部分",
        "subject": "衛生法規與倫理",
        "year": "114",
        "exam_name": "114年公務人員特種考試外交領事人員及外交行政人員考試、國際經濟商務人員考試、民航人員考試、原住民族考試",
        "original_question_number": "一",
        "answer_corrected": false,
        "flags": []
      }
    },
    {
      "id": "aboriginal-77f8735d-0002",
      "exam_id": "aboriginal-77f8735d",
      "question_type": "essay",
      "question": "請回答下列關於「行政救濟」三個子題：\n何謂行政救濟？（10 分）\n構成行政救濟主要的兩大程序及各程序的意涵為何？（10分）\n說明兩大程序間存在何種關係，以及該關係存在的目的？（5分）",
      "options": [],
      "correct_answer": 0,
      "correct_answer_json": null,
      "auto_gradable": false,
      "explanation": null,
      "source_meta": {
        "parser_version": "moex_license_v1.0",
        "parsed_at": "2026-04-25T12:37:39+00:00",
        "source_pdf_sha1": "790637ccbf11",
        "answer_pdf_sha1": null,
        "source_family": "moex-gov-tw",
        "moex": {
          "exam_code": "114140",
          "c": "511",
          "s": "2003",
          "q": "1"
        },
        "raw_section_label": "甲、申論題部分",
        "subject": "衛生法規與倫理",
        "year": "114",
        "exam_name": "114年公務人員特種考試外交領事人員及外交行政人員考試、國際經濟商務人員考試、民航人員考試、原住民族考試",
        "original_question_number": "二",
        "answer_corrected": false,
        "flags": []
      }
    },
    {
      "id": "aboriginal-77f8735d-0003",
      "exam_id": "aboriginal-77f8735d",
      "question_type": "essay",
      "question": "請分述「人體研究」與「人體試驗」的意涵及所依據之法規，並說明兩\n者之差異。（25分）",
      "options": [],
      "correct_answer": 0,
      "correct_answer_json": null,
      "auto_gradable": false,
      "explanation": null,
      "source_meta": {
        "parser_version": "moex_license_v1.0",
        "parsed_at": "2026-04-25T12:37:39+00:00",
        "source_pdf_sha1": "790637ccbf11",
        "answer_pdf_sha1": null,
        "source_family": "moex-gov-tw",
        "moex": {
          "exam_code": "114140",
          "c": "511",
          "s": "2003",
          "q": "1"
        },
        "raw_section_label": "甲、申論題部分",
        "subject": "衛生法規與倫理",
        "year": "114",
        "exam_name": "114年公務人員特種考試外交領事人員及外交行政人員考試、國際經濟商務人員考試、民航人員考試、原住民族考試",
        "original_question_number": "三",
        "answer_corrected": false,
        "flags": []
      }
    },
    {
      "id": "aboriginal-77f8735d-0004",
      "exam_id": "aboriginal-77f8735d",
      "question_type": "essay",
      "question": "全民健康保險法第 43 條規定保險對象應自行負擔門診或急診費用之百\n分之二十，居家照護醫療費用之百分之五。某甲與某乙皆為一般民眾無\n特殊身分；一般狀況下，門診就醫相關費用包含：掛號費、健保醫療費\n用（健保支付＋自行負擔），請回答下列三個子題：\n狀況一：居住於臺北市的某甲到嘉義縣阿里山鄉旅遊，臨時患病於當地\n健保特約診所就醫，請問某甲需支付那些費用，並說明原因。（10分）\n狀況二：居住於澎湖縣七美鄉某乙至臺北市大同區探親，臨時患病於\n臺北市大同區健保特約診所就醫，請問某乙需支付那些費用，並說明\n原因。（10 分）\n請就上述兩個狀況說明支付費用項目差異的可能緣由。（5分）",
      "options": [],
      "correct_answer": 0,
      "correct_answer_json": null,
      "auto_gradable": false,
      "explanation": null,
      "source_meta": {
        "parser_version": "moex_license_v1.0",
        "parsed_at": "2026-04-25T12:37:39+00:00",
        "source_pdf_sha1": "790637ccbf11",
        "answer_pdf_sha1": null,
        "source_family": "moex-gov-tw",
        "moex": {
          "exam_code": "114140",
          "c": "511",
          "s": "2003",
          "q": "1"
        },
        "raw_section_label": "甲、申論題部分",
        "subject": "衛生法規與倫理",
        "year": "114",
        "exam_name": "114年公務人員特種考試外交領事人員及外交行政人員考試、國際經濟商務人員考試、民航人員考試、原住民族考試",
        "original_question_number": "四",
        "answer_corrected": false,
        "flags": []
      }
    },
    {
      "id": "aboriginal-77f8735d-0005",
      "exam_id": "aboriginal-77f8735d",
      "question_type": "essay",
      "question": "跨理論模式（transtheoreticalmodel,TTM）強調行為改變是一個過程，試\n以戒菸為例，說明如何運用跨理論模式於戒菸行為的改變。（25分）",
      "options": [],
      "correct_answer": 0,
      "correct_answer_json": null,
      "auto_gradable": false,
      "explanation": null,
      "source_meta": {
        "parser_version": "moex_license_v1.0",
        "parsed_at": "2026-04-25T12:37:39+00:00",
        "source_pdf_sha1": "a4da5f4bf3a7",
        "answer_pdf_sha1": null,
        "source_family": "moex-gov-tw",
        "moex": {
          "exam_code": "114140",
          "c": "511",
          "s": "2002",
          "q": "1"
        },
        "raw_section_label": "甲、申論題部分",
        "subject": "衛生行政",
        "year": "114",
        "exam_name": "114年公務人員特種考試外交領事人員及外交行政人員考試、國際經濟商務人員考試、民航人員考試、原住民族考試",
        "original_question_number": "一",
        "answer_corrected": false,
        "flags": []
      }
    },
    {
      "id": "aboriginal-77f8735d-0006",
      "exam_id": "aboriginal-77f8735d",
      "question_type": "essay",
      "question": "請說明衛生福利部國民健康署 114 年版最新的成人預防保健服務內容及\n其政策目的。（25 分）",
      "options": [],
      "correct_answer": 0,
      "correct_answer_json": null,
      "auto_gradable": false,
      "explanation": null,
      "source_meta": {
        "parser_version": "moex_license_v1.0",
        "parsed_at": "2026-04-25T12:37:39+00:00",
        "source_pdf_sha1": "a4da5f4bf3a7",
        "answer_pdf_sha1": null,
        "source_family": "moex-gov-tw",
        "moex": {
          "exam_code": "114140",
          "c": "511",
          "s": "2002",
          "q": "1"
        },
        "raw_section_label": "甲、申論題部分",
        "subject": "衛生行政",
        "year": "114",
        "exam_name": "114年公務人員特種考試外交領事人員及外交行政人員考試、國際經濟商務人員考試、民航人員考試、原住民族考試",
        "original_question_number": "二",
        "answer_corrected": false,
        "flags": []
      }
    },
    {
      "id": "aboriginal-77f8735d-0007",
      "exam_id": "aboriginal-77f8735d",
      "question_type": "essay",
      "question": "我國因應老化社會的來臨，行政院公告推出長照十年計畫 3.0（簡稱\n長照 3.0）的政策，請詳述為達成健康老化、在地安老、安寧善終的願景\n之八大目標內容。（25分）",
      "options": [],
      "correct_answer": 0,
      "correct_answer_json": null,
      "auto_gradable": false,
      "explanation": null,
      "source_meta": {
        "parser_version": "moex_license_v1.0",
        "parsed_at": "2026-04-25T12:37:39+00:00",
        "source_pdf_sha1": "a4da5f4bf3a7",
        "answer_pdf_sha1": null,
        "source_family": "moex-gov-tw",
        "moex": {
          "exam_code": "114140",
          "c": "511",
          "s": "2002",
          "q": "1"
        },
        "raw_section_label": "甲、申論題部分",
        "subject": "衛生行政",
        "year": "114",
        "exam_name": "114年公務人員特種考試外交領事人員及外交行政人員考試、國際經濟商務人員考試、民航人員考試、原住民族考試",
        "original_question_number": "三",
        "answer_corrected": false,
        "flags": []
      }
    },
    {
      "id": "aboriginal-77f8735d-0008",
      "exam_id": "aboriginal-77f8735d",
      "question_type": "essay",
      "question": "世界衛生組織指出影響健康結果的主要因素是社會決定因素（social\ndeterminantsofhealth,SDH），請說明健康的社會決定因素之相關內容。\n（25分）",
      "options": [],
      "correct_answer": 0,
      "correct_answer_json": null,
      "auto_gradable": false,
      "explanation": null,
      "source_meta": {
        "parser_version": "moex_license_v1.0",
        "parsed_at": "2026-04-25T12:37:39+00:00",
        "source_pdf_sha1": "a4da5f4bf3a7",
        "answer_pdf_sha1": null,
        "source_family": "moex-gov-tw",
        "moex": {
          "exam_code": "114140",
          "c": "511",
          "s": "2002",
          "q": "1"
        },
        "raw_section_label": "甲、申論題部分",
        "subject": "衛生行政",
        "year": "114",
        "exam_name": "114年公務人員特種考試外交領事人員及外交行政人員考試、國際經濟商務人員考試、民航人員考試、原住民族考試",
        "original_question_number": "四",
        "answer_corrected": false,
        "flags": []
      }
    },
    {
      "id": "aboriginal-77f8735d-0009",
      "exam_id": "aboriginal-77f8735d",
      "question_type": "essay",
      "question": "衛生福利部鼓勵協助醫療院所推動醫療 ESG（Environment, Social,\nGovernance），共同促進國家永續發展，請問醫院的 ESG包含那些內容。\n（25分）",
      "options": [],
      "correct_answer": 0,
      "correct_answer_json": null,
      "auto_gradable": false,
      "explanation": null,
      "source_meta": {
        "parser_version": "moex_license_v1.0",
        "parsed_at": "2026-04-25T12:37:39+00:00",
        "source_pdf_sha1": "b2df7335229f",
        "answer_pdf_sha1": null,
        "source_family": "moex-gov-tw",
        "moex": {
          "exam_code": "114140",
          "c": "511",
          "s": "2001",
          "q": "1"
        },
        "raw_section_label": "甲、申論題部分",
        "subject": "醫療制度與品質管理",
        "year": "114",
        "exam_name": "114年公務人員特種考試外交領事人員及外交行政人員考試、國際經濟商務人員考試、民航人員考試、原住民族考試",
        "original_question_number": "一",
        "answer_corrected": false,
        "flags": []
      }
    },
    {
      "id": "aboriginal-77f8735d-0010",
      "exam_id": "aboriginal-77f8735d",
      "question_type": "essay",
      "question": "行政院持續執行「優化偏鄉醫療精進計畫」，欲改善偏遠地區醫療照護品\n質，拉近城鄉醫療差距，提升全民之健康。試舉出三個偏鄉醫療容易遇\n到的問題並加以說明。（25 分）",
      "options": [],
      "correct_answer": 0,
      "correct_answer_json": null,
      "auto_gradable": false,
      "explanation": null,
      "source_meta": {
        "parser_version": "moex_license_v1.0",
        "parsed_at": "2026-04-25T12:37:39+00:00",
        "source_pdf_sha1": "b2df7335229f",
        "answer_pdf_sha1": null,
        "source_family": "moex-gov-tw",
        "moex": {
          "exam_code": "114140",
          "c": "511",
          "s": "2001",
          "q": "1"
        },
        "raw_section_label": "甲、申論題部分",
        "subject": "醫療制度與品質管理",
        "year": "114",
        "exam_name": "114年公務人員特種考試外交領事人員及外交行政人員考試、國際經濟商務人員考試、民航人員考試、原住民族考試",
        "original_question_number": "二",
        "answer_corrected": false,
        "flags": []
      }
    },
    {
      "id": "aboriginal-77f8735d-0011",
      "exam_id": "aboriginal-77f8735d",
      "question_type": "essay",
      "question": "請說明品管圈（qualitycontrolcircle,QCC）對於醫療機構的效益。（25分）",
      "options": [],
      "correct_answer": 0,
      "correct_answer_json": null,
      "auto_gradable": false,
      "explanation": null,
      "source_meta": {
        "parser_version": "moex_license_v1.0",
        "parsed_at": "2026-04-25T12:37:39+00:00",
        "source_pdf_sha1": "b2df7335229f",
        "answer_pdf_sha1": null,
        "source_family": "moex-gov-tw",
        "moex": {
          "exam_code": "114140",
          "c": "511",
          "s": "2001",
          "q": "1"
        },
        "raw_section_label": "甲、申論題部分",
        "subject": "醫療制度與品質管理",
        "year": "114",
        "exam_name": "114年公務人員特種考試外交領事人員及外交行政人員考試、國際經濟商務人員考試、民航人員考試、原住民族考試",
        "original_question_number": "三",
        "answer_corrected": false,
        "flags": []
      }
    },
    {
      "id": "aboriginal-77f8735d-0012",
      "exam_id": "aboriginal-77f8735d",
      "question_type": "essay",
      "question": "關於診療費用支付方式，可分為回溯性支付制度、前瞻性支付制度、診\n斷關聯群支付制度，請說明三種支付制度的內容。（25分）",
      "options": [],
      "correct_answer": 0,
      "correct_answer_json": null,
      "auto_gradable": false,
      "explanation": null,
      "source_meta": {
        "parser_version": "moex_license_v1.0",
        "parsed_at": "2026-04-25T12:37:39+00:00",
        "source_pdf_sha1": "b2df7335229f",
        "answer_pdf_sha1": null,
        "source_family": "moex-gov-tw",
        "moex": {
          "exam_code": "114140",
          "c": "511",
          "s": "2001",
          "q": "1"
        },
        "raw_section_label": "甲、申論題部分",
        "subject": "醫療制度與品質管理",
        "year": "114",
        "exam_name": "114年公務人員特種考試外交領事人員及外交行政人員考試、國際經濟商務人員考試、民航人員考試、原住民族考試",
        "original_question_number": "四",
        "answer_corrected": false,
        "flags": []
      }
    }
  ]
}