{
  "slug": "heelevel3-e0adf6cd",
  "parser_version": "moex_license_v1.0",
  "parsed_at": "2026-04-25T12:32:36+00:00",
  "paper_count": 30,
  "paper_with_questions": 30,
  "question_count": 234,
  "type_counts": {
    "essay": 109,
    "single_choice": 125
  },
  "issues": [
    {
      "year": "114",
      "subject": "教育哲學",
      "status": "ok",
      "format": "pure_essay",
      "raw_q": 4,
      "answers": 0
    },
    {
      "year": "114",
      "subject": "教育心理學",
      "status": "ok",
      "format": "pure_essay",
      "raw_q": 4,
      "answers": 0
    },
    {
      "year": "114",
      "subject": "教育測驗與統計",
      "status": "ok",
      "format": "pure_essay",
      "raw_q": 4,
      "answers": 0
    },
    {
      "year": "114",
      "subject": "教育行政學",
      "status": "ok",
      "format": "pure_essay",
      "raw_q": 4,
      "answers": 0
    },
    {
      "year": "114",
      "subject": "比較教育",
      "status": "ok",
      "format": "pure_essay",
      "raw_q": 4,
      "answers": 0
    },
    {
      "year": "113",
      "subject": "教育哲學",
      "status": "ok",
      "format": "pure_essay",
      "raw_q": 4,
      "answers": 0
    },
    {
      "year": "113",
      "subject": "教育心理學",
      "status": "ok",
      "format": "pure_essay",
      "raw_q": 4,
      "answers": 0
    },
    {
      "year": "113",
      "subject": "教育測驗與統計",
      "status": "ok",
      "format": "pure_essay",
      "raw_q": 4,
      "answers": 0
    },
    {
      "year": "113",
      "subject": "教育行政學",
      "status": "ok",
      "format": "pure_essay",
      "raw_q": 4,
      "answers": 0
    },
    {
      "year": "113",
      "subject": "比較教育",
      "status": "ok",
      "format": "pure_essay",
      "raw_q": 4,
      "answers": 0
    },
    {
      "year": "112",
      "subject": "教育哲學",
      "status": "ok",
      "format": "pure_essay",
      "raw_q": 4,
      "answers": 0
    },
    {
      "year": "112",
      "subject": "教育心理學",
      "status": "ok",
      "format": "pure_essay",
      "raw_q": 4,
      "answers": 0
    },
    {
      "year": "112",
      "subject": "教育測驗與統計",
      "status": "ok",
      "format": "pure_essay",
      "raw_q": 4,
      "answers": 0
    },
    {
      "year": "112",
      "subject": "教育行政學",
      "status": "ok",
      "format": "pure_essay",
      "raw_q": 4,
      "answers": 0
    },
    {
      "year": "112",
      "subject": "比較教育",
      "status": "ok",
      "format": "pure_essay",
      "raw_q": 4,
      "answers": 0
    },
    {
      "year": "111",
      "subject": "教育哲學",
      "status": "ok",
      "format": "pure_essay",
      "raw_q": 4,
      "answers": 0
    },
    {
      "year": "111",
      "subject": "教育心理學",
      "status": "ok",
      "format": "pure_essay",
      "raw_q": 4,
      "answers": 0
    },
    {
      "year": "111",
      "subject": "教育測驗與統計",
      "status": "ok",
      "format": "pure_essay",
      "raw_q": 4,
      "answers": 0
    },
    {
      "year": "111",
      "subject": "教育行政學",
      "status": "ok",
      "format": "pure_essay",
      "raw_q": 4,
      "answers": 0
    },
    {
      "year": "111",
      "subject": "比較教育",
      "status": "ok",
      "format": "pure_essay",
      "raw_q": 4,
      "answers": 0
    },
    {
      "year": "110",
      "subject": "教育哲學",
      "status": "ok",
      "format": "pure_essay",
      "raw_q": 4,
      "answers": 0
    },
    {
      "year": "110",
      "subject": "教育心理學",
      "status": "ok",
      "format": "pure_essay",
      "raw_q": 4,
      "answers": 0
    },
    {
      "year": "110",
      "subject": "教育測驗與統計",
      "status": "ok",
      "format": "pure_essay",
      "raw_q": 3,
      "answers": 0
    },
    {
      "year": "110",
      "subject": "教育行政學",
      "status": "ok",
      "format": "pure_essay",
      "raw_q": 4,
      "answers": 0
    },
    {
      "year": "110",
      "subject": "比較教育",
      "status": "ok",
      "format": "pure_essay",
      "raw_q": 4,
      "answers": 0
    }
  ]
}