{"batch": 63, "rows": 50, "chunks": ["-- moex_license_ingest questions batch 63/330 (50 rows)\n\nINSERT INTO public.questions (id, exam_id, paper_id, subject_id, chapter_id, question_type, question_text, options, correct_answer, correct_answer_json, auto_gradable, source, is_active, version, source_meta, explanation)\nVALUES\n('bookkeeper-moex-01312', 'bookkeeper', 'bookkeeper-moex-104-12108af6', 'sub-bookkeeper-04', NULL, 'single_choice', '張君於民國102年12月31日自臺中市地方稅務局離職，現在是民國104年11月21日，請問下列敘述何者 正確？ 離職未滿三年，不得執行記帳士職務 離職未滿二年，不得執行記帳士職務 民國102年12月31日離職後，即可在臺中市區域外執行記帳士職務 曾任稅務機關稅務職系人員者，終身不得執行記帳士職務', '[\"\", \"\", \"\", \"\"]'::jsonb, 2, NULL, FALSE, 'official', TRUE, 1, '{\"parser_version\": \"moex_license_v1.0\", \"parsed_at\": \"2026-04-25T04:29:27+00:00\", \"source_pdf_sha1\": \"905d3fabe5f9\", \"answer_pdf_sha1\": \"03ba1485918e\", \"source_family\": \"moex-gov-tw\", \"moex\": {\"exam_code\": \"104170\", \"c\": \"602\", \"s\": \"1201\", \"q\": \"1\"}, \"raw_section_label\": \"本試題為單一選擇題\", \"subject\": \"記帳相關法規概要\", \"year\": \"104\", \"exam_name\": \"104年專技建築師、技師、第二次食品技師、不動產經紀人、記帳士考試\", \"original_question_number\": 23, \"answer_corrected\": false, \"flags\": [\"incomplete_options\"], \"slug\": \"bookkeeper\", \"db_exam_id\": \"bookkeeper\"}'::jsonb, NULL),\n  ('bookkeeper-moex-01313', 'bookkeeper', 'bookkeeper-moex-104-12108af6', 'sub-bookkeeper-04', NULL, 'single_choice', '下列那一項業務非屬記帳士之執行業務範圍？ 受理稅務諮詢事項 受委任辦理各項稅捐稽徵案件之申報及申請事項 受委任辦理各項稅捐稽徵案件之查核簽證申報 受委任辦理營業、變更、註銷、停業、復業或其他登記事項', '[\"\", \"\", \"\", \"\"]'::jsonb, 2, NULL, FALSE, 'official', TRUE, 1, '{\"parser_version\": \"moex_license_v1.0\", \"parsed_at\": \"2026-04-25T04:29:27+00:00\", \"source_pdf_sha1\": \"905d3fabe5f9\", \"answer_pdf_sha1\": \"03ba1485918e\", \"source_family\": \"moex-gov-tw\", \"moex\": {\"exam_code\": \"104170\", \"c\": \"602\", \"s\": \"1201\", \"q\": \"1\"}, \"raw_section_label\": \"本試題為單一選擇題\", \"subject\": \"記帳相關法規概要\", \"year\": \"104\", \"exam_name\": \"104年專技建築師、技師、第二次食品技師、不動產經紀人、記帳士考試\", \"original_question_number\": 24, \"answer_corrected\": false, \"flags\": [\"incomplete_options\"], \"slug\": \"bookkeeper\", \"db_exam_id\": \"bookkeeper\"}'::jsonb, NULL),\n  ('bookkeeper-moex-01314', 'bookkeeper', 'bookkeeper-moex-104-12108af6', 'sub-bookkeeper-04', NULL, 'single_choice', '根據記帳士法第16條規定，記帳士執行業務，應設置簿冊，下列那一項非屬於該條文所列示之載明事項？ 受委任記帳士之姓名及證書字號  委任案件之類別及內容 委任酬勞金額    委任人之姓名或名稱及地址', '[\"\", \"\", \"\", \"\"]'::jsonb, 0, NULL, FALSE, 'official', TRUE, 1, '{\"parser_version\": \"moex_license_v1.0\", \"parsed_at\": \"2026-04-25T04:29:27+00:00\", \"source_pdf_sha1\": \"905d3fabe5f9\", \"answer_pdf_sha1\": \"03ba1485918e\", \"source_family\": \"moex-gov-tw\", \"moex\": {\"exam_code\": \"104170\", \"c\": \"602\", \"s\": \"1201\", \"q\": \"1\"}, \"raw_section_label\": \"本試題為單一選擇題\", \"subject\": \"記帳相關法規概要\", \"year\": \"104\", \"exam_name\": \"104年專技建築師、技師、第二次食品技師、不動產經紀人、記帳士考試\", \"original_question_number\": 25, \"answer_corrected\": false, \"flags\": [\"incomplete_options\"], \"slug\": \"bookkeeper\", \"db_exam_id\": \"bookkeeper\"}'::jsonb, NULL),\n  ('bookkeeper-moex-01315', 'bookkeeper', 'bookkeeper-moex-104-12108af6', 'sub-bookkeeper-04', NULL, 'single_choice', '李記帳士於11月5日收到記帳士懲戒委員會之懲戒處分通知書，請問該通知書應通知李記帳士於何日之前 提出答辯？ 11月15日  11月20日  11月25日  12月5日 依記帳士法第 條規定，記帳士受停止執行業務處分累計滿多少年者應予除名？', '[\"\", \"\", \"\", \"\"]'::jsonb, 2, NULL, FALSE, 'official', TRUE, 1, '{\"parser_version\": \"moex_license_v1.0\", \"parsed_at\": \"2026-04-25T04:29:27+00:00\", \"source_pdf_sha1\": \"905d3fabe5f9\", \"answer_pdf_sha1\": \"03ba1485918e\", \"source_family\": \"moex-gov-tw\", \"moex\": {\"exam_code\": \"104170\", \"c\": \"602\", \"s\": \"1201\", \"q\": \"1\"}, \"raw_section_label\": \"本試題為單一選擇題\", \"subject\": \"記帳相關法規概要\", \"year\": \"104\", \"exam_name\": \"104年專技建築師、技師、第二次食品技師、不動產經紀人、記帳士考試\", \"original_question_number\": 26, \"answer_corrected\": false, \"flags\": [\"incomplete_options\"], \"slug\": \"bookkeeper\", \"db_exam_id\": \"bookkeeper\"}'::jsonb, NULL),\n  ('bookkeeper-moex-01316', 'bookkeeper', 'bookkeeper-moex-104-12108af6', 'sub-bookkeeper-04', NULL, 'single_choice', '27 5年  4年  3年  2年', '[\"\", \"\", \"\", \"\"]'::jsonb, 0, NULL, FALSE, 'official', TRUE, 1, '{\"parser_version\": \"moex_license_v1.0\", \"parsed_at\": \"2026-04-25T04:29:27+00:00\", \"source_pdf_sha1\": \"905d3fabe5f9\", \"answer_pdf_sha1\": \"03ba1485918e\", \"source_family\": \"moex-gov-tw\", \"moex\": {\"exam_code\": \"104170\", \"c\": \"602\", \"s\": \"1201\", \"q\": \"1\"}, \"raw_section_label\": \"本試題為單一選擇題\", \"subject\": \"記帳相關法規概要\", \"year\": \"104\", \"exam_name\": \"104年專技建築師、技師、第二次食品技師、不動產經紀人、記帳士考試\", \"original_question_number\": 27, \"answer_corrected\": false, \"flags\": [\"incomplete_options\"], \"slug\": \"bookkeeper\", \"db_exam_id\": \"bookkeeper\"}'::jsonb, NULL),\n  ('bookkeeper-moex-01317', 'bookkeeper', 'bookkeeper-moex-104-12108af6', 'sub-bookkeeper-04', NULL, 'single_choice', '真頂有限公司為新設立，其擬委外由記帳士處理會計事務，在公司章程沒有額外規定的情況下，下列敘述何 者正確？ 由總經理提報經董事會同意即可 應由董事會以董事過半數之出席，及董事出席過半數之同意 應有全體股東過半數之同意 應有全體股東之同意', '[\"\", \"\", \"\", \"\"]'::jsonb, 2, NULL, FALSE, 'official', TRUE, 1, '{\"parser_version\": \"moex_license_v1.0\", \"parsed_at\": \"2026-04-25T04:29:27+00:00\", \"source_pdf_sha1\": \"905d3fabe5f9\", \"answer_pdf_sha1\": \"03ba1485918e\", \"source_family\": \"moex-gov-tw\", \"moex\": {\"exam_code\": \"104170\", \"c\": \"602\", \"s\": \"1201\", \"q\": \"1\"}, \"raw_section_label\": \"本試題為單一選擇題\", \"subject\": \"記帳相關法規概要\", \"year\": \"104\", \"exam_name\": \"104年專技建築師、技師、第二次食品技師、不動產經紀人、記帳士考試\", \"original_question_number\": 28, \"answer_corrected\": false, \"flags\": [\"incomplete_options\"], \"slug\": \"bookkeeper\", \"db_exam_id\": \"bookkeeper\"}'::jsonb, NULL),\n  ('bookkeeper-moex-01318', 'bookkeeper', 'bookkeeper-moex-104-12108af6', 'sub-bookkeeper-04', NULL, 'single_choice', '下列有關商業應否適用商業會計法之敘述，何者錯誤？ 每月銷售額未達新臺幣20萬元之商業，得不適用商業會計法 每月銷售額未達使用統一發票標準之小規模之合夥或獨資商業，得不適用商業會計法 公營事業會計事務之處理，除其他法律另有規定者外，適用商業會計法 登記資本額新臺幣5萬元以下獨資或合夥商業，得不適用商業會計法', '[\"\", \"\", \"\", \"\"]'::jsonb, 0, NULL, FALSE, 'official', TRUE, 1, '{\"parser_version\": \"moex_license_v1.0\", \"parsed_at\": \"2026-04-25T04:29:27+00:00\", \"source_pdf_sha1\": \"905d3fabe5f9\", \"answer_pdf_sha1\": \"03ba1485918e\", \"source_family\": \"moex-gov-tw\", \"moex\": {\"exam_code\": \"104170\", \"c\": \"602\", \"s\": \"1201\", \"q\": \"1\"}, \"raw_section_label\": \"本試題為單一選擇題\", \"subject\": \"記帳相關法規概要\", \"year\": \"104\", \"exam_name\": \"104年專技建築師、技師、第二次食品技師、不動產經紀人、記帳士考試\", \"original_question_number\": 29, \"answer_corrected\": false, \"flags\": [\"incomplete_options\"], \"slug\": \"bookkeeper\", \"db_exam_id\": \"bookkeeper\"}'::jsonb, NULL),\n  ('bookkeeper-moex-01319', 'bookkeeper', 'bookkeeper-moex-104-12108af6', 'sub-bookkeeper-04', NULL, 'single_choice', '現行商業會計法中有關商業建立會計制度應考慮之事項包括①實際業務情形  ②會計事務之性質  ③內部', '[\"管理上的需要  ⑤商業通用制度規範，下列何者正確？ ⑤\", \"⑤\", \"\", \"\"]'::jsonb, 2, NULL, FALSE, 'official', TRUE, 1, '{\"parser_version\": \"moex_license_v1.0\", \"parsed_at\": \"2026-04-25T04:29:27+00:00\", \"source_pdf_sha1\": \"905d3fabe5f9\", \"answer_pdf_sha1\": \"03ba1485918e\", \"source_family\": \"moex-gov-tw\", \"moex\": {\"exam_code\": \"104170\", \"c\": \"602\", \"s\": \"1201\", \"q\": \"1\"}, \"raw_section_label\": \"本試題為單一選擇題\", \"subject\": \"記帳相關法規概要\", \"year\": \"104\", \"exam_name\": \"104年專技建築師、技師、第二次食品技師、不動產經紀人、記帳士考試\", \"original_question_number\": 30, \"answer_corrected\": false, \"flags\": [\"incomplete_options\"], \"slug\": \"bookkeeper\", \"db_exam_id\": \"bookkeeper\"}'::jsonb, NULL),\n  ('bookkeeper-moex-01320', 'bookkeeper', 'bookkeeper-moex-104-12108af6', 'sub-bookkeeper-04', NULL, 'single_choice', '下列那一項不屬於商業會計法規定之原始憑證？ 計工單    營利事業所得稅核定通知書 理賠給付通知書    銷貨發票', '[\"\", \"\", \"\", \"\"]'::jsonb, 2, NULL, FALSE, 'official', TRUE, 1, '{\"parser_version\": \"moex_license_v1.0\", \"parsed_at\": \"2026-04-25T04:29:27+00:00\", \"source_pdf_sha1\": \"905d3fabe5f9\", \"answer_pdf_sha1\": \"03ba1485918e\", \"source_family\": \"moex-gov-tw\", \"moex\": {\"exam_code\": \"104170\", \"c\": \"602\", \"s\": \"1201\", \"q\": \"1\"}, \"raw_section_label\": \"本試題為單一選擇題\", \"subject\": \"記帳相關法規概要\", \"year\": \"104\", \"exam_name\": \"104年專技建築師、技師、第二次食品技師、不動產經紀人、記帳士考試\", \"original_question_number\": 31, \"answer_corrected\": false, \"flags\": [\"incomplete_options\"], \"slug\": \"bookkeeper\", \"db_exam_id\": \"bookkeeper\"}'::jsonb, NULL),\n  ('bookkeeper-moex-01321', 'bookkeeper', 'bookkeeper-moex-104-12108af6', 'sub-bookkeeper-04', NULL, 'single_choice', '依商業會計法第26條規定，商業會計帳簿所記載之財物帳戶，應載明： 供應商  取得日期  保管人員姓名  存置地點', '[\"\", \"\", \"\", \"\"]'::jsonb, 3, NULL, FALSE, 'official', TRUE, 1, '{\"parser_version\": \"moex_license_v1.0\", \"parsed_at\": \"2026-04-25T04:29:27+00:00\", \"source_pdf_sha1\": \"905d3fabe5f9\", \"answer_pdf_sha1\": \"03ba1485918e\", \"source_family\": \"moex-gov-tw\", \"moex\": {\"exam_code\": \"104170\", \"c\": \"602\", \"s\": \"1201\", \"q\": \"1\"}, \"raw_section_label\": \"本試題為單一選擇題\", \"subject\": \"記帳相關法規概要\", \"year\": \"104\", \"exam_name\": \"104年專技建築師、技師、第二次食品技師、不動產經紀人、記帳士考試\", \"original_question_number\": 32, \"answer_corrected\": false, \"flags\": [\"incomplete_options\"], \"slug\": \"bookkeeper\", \"db_exam_id\": \"bookkeeper\"}'::jsonb, NULL)\nON CONFLICT (id) DO NOTHING;\n", "-- moex_license_ingest questions batch 63/330 (50 rows)\n\nINSERT INTO public.questions (id, exam_id, paper_id, subject_id, chapter_id, question_type, question_text, options, correct_answer, correct_answer_json, auto_gradable, source, is_active, version, source_meta, explanation)\nVALUES\n('bookkeeper-moex-01322', 'bookkeeper', 'bookkeeper-moex-104-12108af6', 'sub-bookkeeper-04', NULL, 'single_choice', '依商業會計法規定，下列有關綜合損益表之敘述何者有誤？ 反映商業報導期間之經營績效 收益，係指報導期間經濟效益之增加，以資產流入或負債減少等方式增加權益，但不含資產增值而增加之 權益 費損，係指報導期間經濟效益之減少，以資產流出、消耗或負債增加等方式減少權益 分配給業主而減少的權益不應當作費損', '[\"\", \"\", \"\", \"\"]'::jsonb, 1, NULL, FALSE, 'official', TRUE, 1, '{\"parser_version\": \"moex_license_v1.0\", \"parsed_at\": \"2026-04-25T04:29:27+00:00\", \"source_pdf_sha1\": \"905d3fabe5f9\", \"answer_pdf_sha1\": \"03ba1485918e\", \"source_family\": \"moex-gov-tw\", \"moex\": {\"exam_code\": \"104170\", \"c\": \"602\", \"s\": \"1201\", \"q\": \"1\"}, \"raw_section_label\": \"本試題為單一選擇題\", \"subject\": \"記帳相關法規概要\", \"year\": \"104\", \"exam_name\": \"104年專技建築師、技師、第二次食品技師、不動產經紀人、記帳士考試\", \"original_question_number\": 33, \"answer_corrected\": false, \"flags\": [\"incomplete_options\"], \"slug\": \"bookkeeper\", \"db_exam_id\": \"bookkeeper\"}'::jsonb, NULL),\n  ('bookkeeper-moex-01323', 'bookkeeper', 'bookkeeper-moex-104-12108af6', 'sub-bookkeeper-04', NULL, 'single_choice', '依公司法規定，任何人得至主管機關之資訊網站查閱之公司登記項目，不包括下列何者？ 公司所在地    董事、監察人姓名及持股 公司章程    經理人姓名', '[\"\", \"\", \"\", \"\"]'::jsonb, 2, NULL, FALSE, 'official', TRUE, 1, '{\"parser_version\": \"moex_license_v1.0\", \"parsed_at\": \"2026-04-25T04:29:27+00:00\", \"source_pdf_sha1\": \"905d3fabe5f9\", \"answer_pdf_sha1\": \"03ba1485918e\", \"source_family\": \"moex-gov-tw\", \"moex\": {\"exam_code\": \"104170\", \"c\": \"602\", \"s\": \"1201\", \"q\": \"1\"}, \"raw_section_label\": \"本試題為單一選擇題\", \"subject\": \"記帳相關法規概要\", \"year\": \"104\", \"exam_name\": \"104年專技建築師、技師、第二次食品技師、不動產經紀人、記帳士考試\", \"original_question_number\": 34, \"answer_corrected\": false, \"flags\": [\"incomplete_options\"], \"slug\": \"bookkeeper\", \"db_exam_id\": \"bookkeeper\"}'::jsonb, NULL),\n  ('bookkeeper-moex-01324', 'bookkeeper', 'bookkeeper-moex-104-12108af6', 'sub-bookkeeper-04', NULL, 'single_choice', '商業在決定財務報表之會計項目金額時，應視實際情形，選擇適當之衡量基礎，不包括下列何者？ 歷史成本  公允價值  淨變現價值  或有價值', '[\"\", \"\", \"\", \"\"]'::jsonb, 3, NULL, FALSE, 'official', TRUE, 1, '{\"parser_version\": \"moex_license_v1.0\", \"parsed_at\": \"2026-04-25T04:29:27+00:00\", \"source_pdf_sha1\": \"905d3fabe5f9\", \"answer_pdf_sha1\": \"03ba1485918e\", \"source_family\": \"moex-gov-tw\", \"moex\": {\"exam_code\": \"104170\", \"c\": \"602\", \"s\": \"1201\", \"q\": \"1\"}, \"raw_section_label\": \"本試題為單一選擇題\", \"subject\": \"記帳相關法規概要\", \"year\": \"104\", \"exam_name\": \"104年專技建築師、技師、第二次食品技師、不動產經紀人、記帳士考試\", \"original_question_number\": 35, \"answer_corrected\": false, \"flags\": [\"incomplete_options\"], \"slug\": \"bookkeeper\", \"db_exam_id\": \"bookkeeper\"}'::jsonb, NULL),\n  ('bookkeeper-moex-01325', 'bookkeeper', 'bookkeeper-moex-104-12108af6', 'sub-bookkeeper-04', NULL, 'single_choice', '按商業會計法規定，具有控制能力或重大影響力之長期股權投資應採用： 成本法  公允價值法  權益法  攤銷後成本法', '[\"\", \"\", \"\", \"\"]'::jsonb, 2, NULL, FALSE, 'official', TRUE, 1, '{\"parser_version\": \"moex_license_v1.0\", \"parsed_at\": \"2026-04-25T04:29:27+00:00\", \"source_pdf_sha1\": \"905d3fabe5f9\", \"answer_pdf_sha1\": \"03ba1485918e\", \"source_family\": \"moex-gov-tw\", \"moex\": {\"exam_code\": \"104170\", \"c\": \"602\", \"s\": \"1201\", \"q\": \"1\"}, \"raw_section_label\": \"本試題為單一選擇題\", \"subject\": \"記帳相關法規概要\", \"year\": \"104\", \"exam_name\": \"104年專技建築師、技師、第二次食品技師、不動產經紀人、記帳士考試\", \"original_question_number\": 36, \"answer_corrected\": false, \"flags\": [\"incomplete_options\"], \"slug\": \"bookkeeper\", \"db_exam_id\": \"bookkeeper\"}'::jsonb, NULL),\n  ('bookkeeper-moex-01326', 'bookkeeper', 'bookkeeper-moex-104-12108af6', 'sub-bookkeeper-04', NULL, 'single_choice', '台逢公司以一運輸設備交換德力公司機器設備一部，德力公司之機器設備公允價值$400,000，台逢公司的運輸 設備成本$600,000，累計折舊$300,000，沒有公允價值，依交易條件，台逢另外支付現金$50,000 給德力，請 問台逢公司換入之機器設備入帳金額為何？ $400,000  $300,000  $600,000  $350,000', '[\"\", \"\", \"\", \"\"]'::jsonb, 0, NULL, FALSE, 'official', TRUE, 1, '{\"parser_version\": \"moex_license_v1.0\", \"parsed_at\": \"2026-04-25T04:29:27+00:00\", \"source_pdf_sha1\": \"905d3fabe5f9\", \"answer_pdf_sha1\": \"03ba1485918e\", \"source_family\": \"moex-gov-tw\", \"moex\": {\"exam_code\": \"104170\", \"c\": \"602\", \"s\": \"1201\", \"q\": \"1\"}, \"raw_section_label\": \"本試題為單一選擇題\", \"subject\": \"記帳相關法規概要\", \"year\": \"104\", \"exam_name\": \"104年專技建築師、技師、第二次食品技師、不動產經紀人、記帳士考試\", \"original_question_number\": 37, \"answer_corrected\": false, \"flags\": [\"incomplete_options\"], \"slug\": \"bookkeeper\", \"db_exam_id\": \"bookkeeper\"}'::jsonb, NULL),\n  ('bookkeeper-moex-01327', 'bookkeeper', 'bookkeeper-moex-104-12108af6', 'sub-bookkeeper-04', NULL, 'single_choice', '下列有關應收帳款之會計處理，何者錯誤？ 應收款項之衡量應以扣除估計之備抵呆帳後之餘額為準 應設置備抵呆帳項目 其已確定為呆帳者，應認列呆帳費用 屬營業發生與非營業發生之應收帳款及應收票據應分別列示', '[\"\", \"\", \"\", \"\"]'::jsonb, 2, NULL, FALSE, 'official', TRUE, 1, '{\"parser_version\": \"moex_license_v1.0\", \"parsed_at\": \"2026-04-25T04:29:27+00:00\", \"source_pdf_sha1\": \"905d3fabe5f9\", \"answer_pdf_sha1\": \"03ba1485918e\", \"source_family\": \"moex-gov-tw\", \"moex\": {\"exam_code\": \"104170\", \"c\": \"602\", \"s\": \"1201\", \"q\": \"1\"}, \"raw_section_label\": \"本試題為單一選擇題\", \"subject\": \"記帳相關法規概要\", \"year\": \"104\", \"exam_name\": \"104年專技建築師、技師、第二次食品技師、不動產經紀人、記帳士考試\", \"original_question_number\": 38, \"answer_corrected\": false, \"flags\": [\"incomplete_options\"], \"slug\": \"bookkeeper\", \"db_exam_id\": \"bookkeeper\"}'::jsonb, NULL),\n  ('bookkeeper-moex-01328', 'bookkeeper', 'bookkeeper-moex-104-12108af6', 'sub-bookkeeper-04', NULL, 'single_choice', '依商業會計法對於費用及損失之規定，下列敘述何者正確？ 商業有支付員工退休金之義務者，應於支付時認列為當期費用 具有負債性質之特別股，其股利應認列為費用 商業對業主分配之盈餘，應作為當期費用 費用之抵銷額可列為收入', '[\"\", \"\", \"\", \"\"]'::jsonb, 1, NULL, FALSE, 'official', TRUE, 1, '{\"parser_version\": \"moex_license_v1.0\", \"parsed_at\": \"2026-04-25T04:29:27+00:00\", \"source_pdf_sha1\": \"905d3fabe5f9\", \"answer_pdf_sha1\": \"03ba1485918e\", \"source_family\": \"moex-gov-tw\", \"moex\": {\"exam_code\": \"104170\", \"c\": \"602\", \"s\": \"1201\", \"q\": \"1\"}, \"raw_section_label\": \"本試題為單一選擇題\", \"subject\": \"記帳相關法規概要\", \"year\": \"104\", \"exam_name\": \"104年專技建築師、技師、第二次食品技師、不動產經紀人、記帳士考試\", \"original_question_number\": 39, \"answer_corrected\": false, \"flags\": [\"incomplete_options\"], \"slug\": \"bookkeeper\", \"db_exam_id\": \"bookkeeper\"}'::jsonb, NULL),\n  ('bookkeeper-moex-01329', 'bookkeeper', 'bookkeeper-moex-104-12108af6', 'sub-bookkeeper-04', NULL, 'single_choice', '依商業會計法之規定，營業收入認列時點為： 採用現金收付制之商業，應於交付貨品時 採用權責發生制之商業，應於現金收付時 勞務收入依其性質分段提供者，應於勞務提供完成時 分期付款銷貨收入得視其性質按毛利百分比攤算入帳', '[\"\", \"\", \"\", \"\"]'::jsonb, 3, NULL, FALSE, 'official', TRUE, 1, '{\"parser_version\": \"moex_license_v1.0\", \"parsed_at\": \"2026-04-25T04:29:27+00:00\", \"source_pdf_sha1\": \"905d3fabe5f9\", \"answer_pdf_sha1\": \"03ba1485918e\", \"source_family\": \"moex-gov-tw\", \"moex\": {\"exam_code\": \"104170\", \"c\": \"602\", \"s\": \"1201\", \"q\": \"1\"}, \"raw_section_label\": \"本試題為單一選擇題\", \"subject\": \"記帳相關法規概要\", \"year\": \"104\", \"exam_name\": \"104年專技建築師、技師、第二次食品技師、不動產經紀人、記帳士考試\", \"original_question_number\": 40, \"answer_corrected\": false, \"flags\": [\"incomplete_options\"], \"slug\": \"bookkeeper\", \"db_exam_id\": \"bookkeeper\"}'::jsonb, NULL),\n  ('bookkeeper-moex-01330', 'bookkeeper', 'bookkeeper-moex-104-12108af6', 'sub-bookkeeper-04', NULL, 'single_choice', '商業之決算，應於會計年度終了後幾個月內辦理完竣？必要時得延長多久？ 4個月；2個月  2個月；2個月  2個月；2個半月  4個月；2個半月', '[\"\", \"\", \"\", \"\"]'::jsonb, 2, NULL, FALSE, 'official', TRUE, 1, '{\"parser_version\": \"moex_license_v1.0\", \"parsed_at\": \"2026-04-25T04:29:27+00:00\", \"source_pdf_sha1\": \"905d3fabe5f9\", \"answer_pdf_sha1\": \"03ba1485918e\", \"source_family\": \"moex-gov-tw\", \"moex\": {\"exam_code\": \"104170\", \"c\": \"602\", \"s\": \"1201\", \"q\": \"1\"}, \"raw_section_label\": \"本試題為單一選擇題\", \"subject\": \"記帳相關法規概要\", \"year\": \"104\", \"exam_name\": \"104年專技建築師、技師、第二次食品技師、不動產經紀人、記帳士考試\", \"original_question_number\": 41, \"answer_corrected\": false, \"flags\": [\"incomplete_options\"], \"slug\": \"bookkeeper\", \"db_exam_id\": \"bookkeeper\"}'::jsonb, NULL),\n  ('bookkeeper-moex-01331', 'bookkeeper', 'bookkeeper-moex-104-12108af6', 'sub-bookkeeper-04', NULL, 'single_choice', '商業負責人、主辦及經辦會計人員或依法受託他人處理會計事務之人員，有下列何種行為，將被處5年以下 有期徒刑、拘役或科或併科新臺幣60萬元以下罰金？ 以明知為不實之事項，而填製會計憑證或記入帳冊 毀損會計帳簿頁數，或毀滅審計軌跡 不取得原始憑證或給予他人憑證 未依商業會計法第38條規定期限保存會計帳簿、報表或憑證', '[\"\", \"\", \"\", \"\"]'::jsonb, 0, NULL, FALSE, 'official', TRUE, 1, '{\"parser_version\": \"moex_license_v1.0\", \"parsed_at\": \"2026-04-25T04:29:27+00:00\", \"source_pdf_sha1\": \"905d3fabe5f9\", \"answer_pdf_sha1\": \"03ba1485918e\", \"source_family\": \"moex-gov-tw\", \"moex\": {\"exam_code\": \"104170\", \"c\": \"602\", \"s\": \"1201\", \"q\": \"1\"}, \"raw_section_label\": \"本試題為單一選擇題\", \"subject\": \"記帳相關法規概要\", \"year\": \"104\", \"exam_name\": \"104年專技建築師、技師、第二次食品技師、不動產經紀人、記帳士考試\", \"original_question_number\": 42, \"answer_corrected\": false, \"flags\": [\"incomplete_options\"], \"slug\": \"bookkeeper\", \"db_exam_id\": \"bookkeeper\"}'::jsonb, NULL)\nON CONFLICT (id) DO NOTHING;\n", "-- moex_license_ingest questions batch 63/330 (50 rows)\n\nINSERT INTO public.questions (id, exam_id, paper_id, subject_id, chapter_id, question_type, question_text, options, correct_answer, correct_answer_json, auto_gradable, source, is_active, version, source_meta, explanation)\nVALUES\n('bookkeeper-moex-01332', 'bookkeeper', 'bookkeeper-moex-104-12108af6', 'sub-bookkeeper-04', NULL, 'single_choice', '張君未依法取得代他人處理會計事務之資格，而擅自代他人處理商業會計事務，這是他二年內第二次被查 獲，將受那一種處罰？ 處新臺幣6萬元以上30萬元以下罰鍰 處新臺幣60萬元以下罰鍰 處1年以下有期徒刑、拘役或科或併科新臺幣15萬元以下罰金 處1年以下有期徒刑、拘役或科或併科新臺幣60萬元以下罰金', '[\"\", \"\", \"\", \"\"]'::jsonb, 2, NULL, FALSE, 'official', TRUE, 1, '{\"parser_version\": \"moex_license_v1.0\", \"parsed_at\": \"2026-04-25T04:29:27+00:00\", \"source_pdf_sha1\": \"905d3fabe5f9\", \"answer_pdf_sha1\": \"03ba1485918e\", \"source_family\": \"moex-gov-tw\", \"moex\": {\"exam_code\": \"104170\", \"c\": \"602\", \"s\": \"1201\", \"q\": \"1\"}, \"raw_section_label\": \"本試題為單一選擇題\", \"subject\": \"記帳相關法規概要\", \"year\": \"104\", \"exam_name\": \"104年專技建築師、技師、第二次食品技師、不動產經紀人、記帳士考試\", \"original_question_number\": 43, \"answer_corrected\": false, \"flags\": [\"incomplete_options\"], \"slug\": \"bookkeeper\", \"db_exam_id\": \"bookkeeper\"}'::jsonb, NULL),\n  ('bookkeeper-moex-01333', 'bookkeeper', 'bookkeeper-moex-104-12108af6', 'sub-bookkeeper-04', NULL, 'single_choice', '根據公司法第10條規定，下列何者非屬由主管機關得依職權或利害關係人之申請，命令解散之事由？ 公司設立登記後6個月尚未開始營業，且未辦妥延展登記者 公司名稱經法院判決不得使用，依期限規定辦理名稱變更登記仍未辦妥者 公司未於期限內，檢送經會計師查核簽證之申請設立登記資本額的文件 公司負責人拒絕主管機關派員檢查公司業務及財務狀況', '[\"\", \"\", \"\", \"\"]'::jsonb, 3, NULL, FALSE, 'official', TRUE, 1, '{\"parser_version\": \"moex_license_v1.0\", \"parsed_at\": \"2026-04-25T04:29:27+00:00\", \"source_pdf_sha1\": \"905d3fabe5f9\", \"answer_pdf_sha1\": \"03ba1485918e\", \"source_family\": \"moex-gov-tw\", \"moex\": {\"exam_code\": \"104170\", \"c\": \"602\", \"s\": \"1201\", \"q\": \"1\"}, \"raw_section_label\": \"本試題為單一選擇題\", \"subject\": \"記帳相關法規概要\", \"year\": \"104\", \"exam_name\": \"104年專技建築師、技師、第二次食品技師、不動產經紀人、記帳士考試\", \"original_question_number\": 44, \"answer_corrected\": false, \"flags\": [\"incomplete_options\"], \"slug\": \"bookkeeper\", \"db_exam_id\": \"bookkeeper\"}'::jsonb, NULL),\n  ('bookkeeper-moex-01334', 'bookkeeper', 'bookkeeper-moex-104-12108af6', 'sub-bookkeeper-04', NULL, 'single_choice', '下列有關有限公司之敘述，何者正確？ 至少2人以上股東所組織  股東就其出資額為限對公司負其責任 執行業務股東為當然負責人  可經全體股東同意為他公司無限責任股東', '[\"\", \"\", \"\", \"\"]'::jsonb, 1, NULL, FALSE, 'official', TRUE, 1, '{\"parser_version\": \"moex_license_v1.0\", \"parsed_at\": \"2026-04-25T04:29:27+00:00\", \"source_pdf_sha1\": \"905d3fabe5f9\", \"answer_pdf_sha1\": \"03ba1485918e\", \"source_family\": \"moex-gov-tw\", \"moex\": {\"exam_code\": \"104170\", \"c\": \"602\", \"s\": \"1201\", \"q\": \"1\"}, \"raw_section_label\": \"本試題為單一選擇題\", \"subject\": \"記帳相關法規概要\", \"year\": \"104\", \"exam_name\": \"104年專技建築師、技師、第二次食品技師、不動產經紀人、記帳士考試\", \"original_question_number\": 45, \"answer_corrected\": false, \"flags\": [\"incomplete_options\"], \"slug\": \"bookkeeper\", \"db_exam_id\": \"bookkeeper\"}'::jsonb, NULL),\n  ('bookkeeper-moex-01335', 'bookkeeper', 'bookkeeper-moex-104-12108af6', 'sub-bookkeeper-04', NULL, 'single_choice', '依公司法規定，在章程沒有較高規定下，股份有限公司經理人之報酬應由下列何者決定？ 全體股東過半數同意 董事會以董事過半數之出席，及出席董事三分之二同意之決議行之 董事會以董事過半數之出席，及出席董事二分之一同意之決議行之 董事長決定', '[\"\", \"\", \"\", \"\"]'::jsonb, 2, NULL, FALSE, 'official', TRUE, 1, '{\"parser_version\": \"moex_license_v1.0\", \"parsed_at\": \"2026-04-25T04:29:27+00:00\", \"source_pdf_sha1\": \"905d3fabe5f9\", \"answer_pdf_sha1\": \"03ba1485918e\", \"source_family\": \"moex-gov-tw\", \"moex\": {\"exam_code\": \"104170\", \"c\": \"602\", \"s\": \"1201\", \"q\": \"1\"}, \"raw_section_label\": \"本試題為單一選擇題\", \"subject\": \"記帳相關法規概要\", \"year\": \"104\", \"exam_name\": \"104年專技建築師、技師、第二次食品技師、不動產經紀人、記帳士考試\", \"original_question_number\": 46, \"answer_corrected\": false, \"flags\": [\"incomplete_options\"], \"slug\": \"bookkeeper\", \"db_exam_id\": \"bookkeeper\"}'::jsonb, NULL),\n  ('bookkeeper-moex-01336', 'bookkeeper', 'bookkeeper-moex-104-12108af6', 'sub-bookkeeper-04', NULL, 'single_choice', '下列敘述何者正確？ 公司法所稱之中央主管機關為財政部；在直轄市為直轄市政府 公司申請設立之資本額，應經律師查核簽證 公司非在中央主管機關登記後，不得成立 中央主管機關不得委任所屬機關、委託或委辦其他機關辦理本法所規定之事項', '[\"\", \"\", \"\", \"\"]'::jsonb, 2, NULL, FALSE, 'official', TRUE, 1, '{\"parser_version\": \"moex_license_v1.0\", \"parsed_at\": \"2026-04-25T04:29:27+00:00\", \"source_pdf_sha1\": \"905d3fabe5f9\", \"answer_pdf_sha1\": \"03ba1485918e\", \"source_family\": \"moex-gov-tw\", \"moex\": {\"exam_code\": \"104170\", \"c\": \"602\", \"s\": \"1201\", \"q\": \"1\"}, \"raw_section_label\": \"本試題為單一選擇題\", \"subject\": \"記帳相關法規概要\", \"year\": \"104\", \"exam_name\": \"104年專技建築師、技師、第二次食品技師、不動產經紀人、記帳士考試\", \"original_question_number\": 47, \"answer_corrected\": false, \"flags\": [\"incomplete_options\"], \"slug\": \"bookkeeper\", \"db_exam_id\": \"bookkeeper\"}'::jsonb, NULL),\n  ('bookkeeper-moex-01337', 'bookkeeper', 'bookkeeper-moex-104-12108af6', 'sub-bookkeeper-04', NULL, 'single_choice', '依行政程序法規定，違法行政處分於法定救濟期間經過後，下列何者得依職權為全部或一部之撤銷？ 原處分機關或其上級機關  僅原處分機關 僅上級機關    行政法院', '[\"\", \"\", \"\", \"\"]'::jsonb, 0, NULL, FALSE, 'official', TRUE, 1, '{\"parser_version\": \"moex_license_v1.0\", \"parsed_at\": \"2026-04-25T04:29:27+00:00\", \"source_pdf_sha1\": \"905d3fabe5f9\", \"answer_pdf_sha1\": \"03ba1485918e\", \"source_family\": \"moex-gov-tw\", \"moex\": {\"exam_code\": \"104170\", \"c\": \"602\", \"s\": \"1201\", \"q\": \"1\"}, \"raw_section_label\": \"本試題為單一選擇題\", \"subject\": \"記帳相關法規概要\", \"year\": \"104\", \"exam_name\": \"104年專技建築師、技師、第二次食品技師、不動產經紀人、記帳士考試\", \"original_question_number\": 48, \"answer_corrected\": false, \"flags\": [\"incomplete_options\"], \"slug\": \"bookkeeper\", \"db_exam_id\": \"bookkeeper\"}'::jsonb, NULL),\n  ('bookkeeper-moex-01338', 'bookkeeper', 'bookkeeper-moex-104-12108af6', 'sub-bookkeeper-04', NULL, 'single_choice', '下列何者非屬行政處分之要素？ 公法行為    行政機關之行為 具體及抽象事件所為之行為  對外直接發生法律效果', '[\"\", \"\", \"\", \"\"]'::jsonb, 2, NULL, FALSE, 'official', TRUE, 1, '{\"parser_version\": \"moex_license_v1.0\", \"parsed_at\": \"2026-04-25T04:29:27+00:00\", \"source_pdf_sha1\": \"905d3fabe5f9\", \"answer_pdf_sha1\": \"03ba1485918e\", \"source_family\": \"moex-gov-tw\", \"moex\": {\"exam_code\": \"104170\", \"c\": \"602\", \"s\": \"1201\", \"q\": \"1\"}, \"raw_section_label\": \"本試題為單一選擇題\", \"subject\": \"記帳相關法規概要\", \"year\": \"104\", \"exam_name\": \"104年專技建築師、技師、第二次食品技師、不動產經紀人、記帳士考試\", \"original_question_number\": 49, \"answer_corrected\": false, \"flags\": [\"incomplete_options\"], \"slug\": \"bookkeeper\", \"db_exam_id\": \"bookkeeper\"}'::jsonb, NULL),\n  ('bookkeeper-moex-01339', 'bookkeeper', 'bookkeeper-moex-104-12108af6', 'sub-bookkeeper-04', NULL, 'single_choice', '按行政程序法第121條第2項規定之補償請求權，自處分撤銷時起逾幾年不行使而消滅？ 5年  4年  3年  2年', '[\"\", \"\", \"\", \"\"]'::jsonb, 0, NULL, FALSE, 'official', TRUE, 1, '{\"parser_version\": \"moex_license_v1.0\", \"parsed_at\": \"2026-04-25T04:29:27+00:00\", \"source_pdf_sha1\": \"905d3fabe5f9\", \"answer_pdf_sha1\": \"03ba1485918e\", \"source_family\": \"moex-gov-tw\", \"moex\": {\"exam_code\": \"104170\", \"c\": \"602\", \"s\": \"1201\", \"q\": \"1\"}, \"raw_section_label\": \"本試題為單一選擇題\", \"subject\": \"記帳相關法規概要\", \"year\": \"104\", \"exam_name\": \"104年專技建築師、技師、第二次食品技師、不動產經紀人、記帳士考試\", \"original_question_number\": 50, \"answer_corrected\": false, \"flags\": [\"incomplete_options\"], \"slug\": \"bookkeeper\", \"db_exam_id\": \"bookkeeper\"}'::jsonb, NULL),\n  ('bookkeeper-moex-01340', 'bookkeeper', 'bookkeeper-moex-103-d35177eb', 'sub-bookkeeper-01', NULL, 'essay', '請作甲貿易公司下列各項交易之分錄（其會計年度為曆年制）：\n從日本進口 1,000 箱之蘋果，起運點交貨每箱報價$2,500；此外，公司尚支付海\n運費$50,000、海上保險費$5,000、貨物稅$10,000、關稅$6,000、報關費$12,000\n及貨櫃車運費$15,000。然而，農業單位抽驗該批蘋果時，卻發現有農藥殘留過\n高的問題，於是擴大抽樣數量，因而延誤提貨的時間，造成若干蘋果品質受損而\n無法出售，經檢查後只有800箱可供出售。根據過去之經驗，一般正常情況下，\n正常損壞率為 5%。假設公司使用永續盤存制記錄存貨，且上述各項支出皆以現\n金支付，請先計算每箱蘋果之進貨成本（四捨五入，計算至元即可），並作該項\n進貨分錄。（6分）\n在2014年1月1日，以現金$50,000另加一張一年期，無息，面額$540,000之本\n票購買一部貨車作為載運貨物之用，當時之公平利率為8%，請作2014年1月1日\n取得該部貨車及2014年12月31日相關之調整分錄（無須作折舊之調整分錄）。\n（6分）\n公司因資金周轉的需要，將2014年10月20日收到面額$3,000,000、利率3%、\n90 天到期的票據於 2014 年 12 月 19 日向銀行貼現，貼現率為 5%，試作應收票\n據貼現時的會計分錄（假設一年為360天）。（6分）', '[]'::jsonb, 0, NULL, FALSE, 'official', TRUE, 1, '{\"parser_version\": \"moex_license_v1.0\", \"parsed_at\": \"2026-04-25T04:29:27+00:00\", \"source_pdf_sha1\": \"eb7c2b3095ad\", \"answer_pdf_sha1\": null, \"source_family\": \"moex-gov-tw\", \"moex\": {\"exam_code\": \"103170\", \"c\": \"602\", \"s\": \"1302\", \"q\": \"1\"}, \"raw_section_label\": \"甲、申論題部分\", \"subject\": \"會計學概要\", \"year\": \"103\", \"exam_name\": \"103年專門建築師技師第二次食品技師考試不動產經紀人記帳士考試\", \"original_question_number\": \"一\", \"answer_corrected\": false, \"flags\": [], \"slug\": \"bookkeeper\", \"db_exam_id\": \"bookkeeper\"}'::jsonb, NULL),\n  ('bookkeeper-moex-01341', 'bookkeeper', 'bookkeeper-moex-103-d35177eb', 'sub-bookkeeper-01', NULL, 'essay', '乙公司X1年結帳後應收帳款為借餘$286,000，備抵呆帳為貸餘$8,800，X2年度有\n關之交易彙總如下：\n㉑銷貨（全部為賒銷）$2,580,000\n㉒銷貨退回$44,600\n㉓收回應收帳款$2,372,000\n㉔沖銷呆帳$10,500\nX2年底分析應收帳款後，估計其中約有$12,600可能無法收回，試作：\n將上述四項交易作成分錄。（8分）\nX2年度呆帳費用提列分錄。（3分）\n計算X2年底應收帳款之淨變現價值。（3分）', '[]'::jsonb, 0, NULL, FALSE, 'official', TRUE, 1, '{\"parser_version\": \"moex_license_v1.0\", \"parsed_at\": \"2026-04-25T04:29:27+00:00\", \"source_pdf_sha1\": \"eb7c2b3095ad\", \"answer_pdf_sha1\": null, \"source_family\": \"moex-gov-tw\", \"moex\": {\"exam_code\": \"103170\", \"c\": \"602\", \"s\": \"1302\", \"q\": \"1\"}, \"raw_section_label\": \"甲、申論題部分\", \"subject\": \"會計學概要\", \"year\": \"103\", \"exam_name\": \"103年專門建築師技師第二次食品技師考試不動產經紀人記帳士考試\", \"original_question_number\": \"二\", \"answer_corrected\": false, \"flags\": [], \"slug\": \"bookkeeper\", \"db_exam_id\": \"bookkeeper\"}'::jsonb, NULL)\nON CONFLICT (id) DO NOTHING;\n", "-- moex_license_ingest questions batch 63/330 (50 rows)\n\nINSERT INTO public.questions (id, exam_id, paper_id, subject_id, chapter_id, question_type, question_text, options, correct_answer, correct_answer_json, auto_gradable, source, is_active, version, source_meta, explanation)\nVALUES\n('bookkeeper-moex-01342', 'bookkeeper', 'bookkeeper-moex-103-d35177eb', 'sub-bookkeeper-01', NULL, 'essay', '請回答下列有關現金流量表的問題，每一問題皆須詳列計算過程，否則不予計分：\n當年度銷貨收入淨額為$15,000,000，部分會計科目期初及期末餘額如下：\n會計科目    期初餘額 期末餘額\n應收帳款  $5,500,000 $5,800,000\n應付帳款          3,400,000 3,800,000\n預收銷貨收入    600,000 500,000\n存貨    1,200,000 1,000,000\n試問：當年度因銷貨交易所收取的現金。（6分）\n公司於當年10月30日以$900,000（支付$300,000之現金及市值$600,000之公司\n股票）購入持股100%之子公司，當時子公司之淨資產如下：\n現金       $80,000\n約當現金   100,000\n存貨       150,000\n應收帳款   230,000\n固定資產   500,000\n應付帳款 （110,000）\n長期負債 （300,000）\n淨資產    $650,000\n試問：該項交易於當年度現金流量表中，屬那一類活動之現金流量？其現金及約\n當現金支出或流入多少？（6分）\n公司於當年大幅更換辦公室之設備，當年度與設備相關科目變動之資料如下：\n會計科目    期初餘額 期末餘額\n設備  $96,000 $120,000\n累計折舊    60,000 36,000\n應付設備款    30,000 40,000\n其他補充資料如下：當年度將舊設備以現金價格$12,000出售，其成本為$72,000、\n累計折舊為$48,000。\n試問：當年新購設備成本為何？當年因增添及處分設備而流出或流入多少現金？\n（6分）', '[]'::jsonb, 0, NULL, FALSE, 'official', TRUE, 1, '{\"parser_version\": \"moex_license_v1.0\", \"parsed_at\": \"2026-04-25T04:29:27+00:00\", \"source_pdf_sha1\": \"eb7c2b3095ad\", \"answer_pdf_sha1\": null, \"source_family\": \"moex-gov-tw\", \"moex\": {\"exam_code\": \"103170\", \"c\": \"602\", \"s\": \"1302\", \"q\": \"1\"}, \"raw_section_label\": \"甲、申論題部分\", \"subject\": \"會計學概要\", \"year\": \"103\", \"exam_name\": \"103年專門建築師技師第二次食品技師考試不動產經紀人記帳士考試\", \"original_question_number\": \"三\", \"answer_corrected\": false, \"flags\": [], \"slug\": \"bookkeeper\", \"db_exam_id\": \"bookkeeper\"}'::jsonb, NULL),\n  ('bookkeeper-moex-01343', 'bookkeeper', 'bookkeeper-moex-103-d35177eb', 'sub-bookkeeper-01', NULL, 'single_choice', '財務會計應遵循下列何者處理？', '[\"業主指示\", \"稅法規定\", \"一般公認會計原則\", \"管理理念\"]'::jsonb, 2, NULL, TRUE, 'official', TRUE, 1, '{\"parser_version\": \"moex_license_v1.0\", \"parsed_at\": \"2026-04-25T04:29:27+00:00\", \"source_pdf_sha1\": \"eb7c2b3095ad\", \"answer_pdf_sha1\": \"151da49cfd80\", \"source_family\": \"moex-gov-tw\", \"moex\": {\"exam_code\": \"103170\", \"c\": \"602\", \"s\": \"1302\", \"q\": \"1\"}, \"raw_section_label\": \"乙、測驗題部分\", \"subject\": \"會計學概要\", \"year\": \"103\", \"exam_name\": \"103年專門建築師技師第二次食品技師考試不動產經紀人記帳士考試\", \"original_question_number\": 1, \"answer_corrected\": false, \"flags\": [], \"slug\": \"bookkeeper\", \"db_exam_id\": \"bookkeeper\"}'::jsonb, NULL),\n  ('bookkeeper-moex-01344', 'bookkeeper', 'bookkeeper-moex-103-d35177eb', 'sub-bookkeeper-01', NULL, 'single_choice', '會計處理程序正確的順序為：', '[\"衡量、認定、記錄、溝通\", \"認定、記錄、衡量、溝通\", \"認定、衡量、記錄、溝通\", \"認定、記錄、溝通、衡量\"]'::jsonb, 2, NULL, TRUE, 'official', TRUE, 1, '{\"parser_version\": \"moex_license_v1.0\", \"parsed_at\": \"2026-04-25T04:29:27+00:00\", \"source_pdf_sha1\": \"eb7c2b3095ad\", \"answer_pdf_sha1\": \"151da49cfd80\", \"source_family\": \"moex-gov-tw\", \"moex\": {\"exam_code\": \"103170\", \"c\": \"602\", \"s\": \"1302\", \"q\": \"1\"}, \"raw_section_label\": \"乙、測驗題部分\", \"subject\": \"會計學概要\", \"year\": \"103\", \"exam_name\": \"103年專門建築師技師第二次食品技師考試不動產經紀人記帳士考試\", \"original_question_number\": 2, \"answer_corrected\": false, \"flags\": [], \"slug\": \"bookkeeper\", \"db_exam_id\": \"bookkeeper\"}'::jsonb, NULL),\n  ('bookkeeper-moex-01345', 'bookkeeper', 'bookkeeper-moex-103-d35177eb', 'sub-bookkeeper-01', NULL, 'single_choice', '甲公司年底調整前試算表上之收入為$30,000，費用為$17,000，必須調整之事項為：預收收益已實現部分 為$2,500、本期折舊$1,200及已賺得但尚未入帳之收益有$2,000，則本期淨利為何？', '[\"$16,300\", \"$12,300\", \"$11,300\", \"$7,300\"]'::jsonb, 0, NULL, TRUE, 'official', TRUE, 1, '{\"parser_version\": \"moex_license_v1.0\", \"parsed_at\": \"2026-04-25T04:29:27+00:00\", \"source_pdf_sha1\": \"eb7c2b3095ad\", \"answer_pdf_sha1\": \"151da49cfd80\", \"source_family\": \"moex-gov-tw\", \"moex\": {\"exam_code\": \"103170\", \"c\": \"602\", \"s\": \"1302\", \"q\": \"1\"}, \"raw_section_label\": \"乙、測驗題部分\", \"subject\": \"會計學概要\", \"year\": \"103\", \"exam_name\": \"103年專門建築師技師第二次食品技師考試不動產經紀人記帳士考試\", \"original_question_number\": 3, \"answer_corrected\": false, \"flags\": [], \"slug\": \"bookkeeper\", \"db_exam_id\": \"bookkeeper\"}'::jsonb, NULL),\n  ('bookkeeper-moex-01346', 'bookkeeper', 'bookkeeper-moex-103-d35177eb', 'sub-bookkeeper-01', NULL, 'single_choice', '甲公司一月初業主權益$400,000，一月底業主權益$500,000，一月份收入$670,000，業主提取$30,000， 本月業主無增資，則一月份費用為：', '[\"$740,000\", \"$770,000\", \"$570,000\", \"$540,000\"]'::jsonb, 3, NULL, TRUE, 'official', TRUE, 1, '{\"parser_version\": \"moex_license_v1.0\", \"parsed_at\": \"2026-04-25T04:29:27+00:00\", \"source_pdf_sha1\": \"eb7c2b3095ad\", \"answer_pdf_sha1\": \"151da49cfd80\", \"source_family\": \"moex-gov-tw\", \"moex\": {\"exam_code\": \"103170\", \"c\": \"602\", \"s\": \"1302\", \"q\": \"1\"}, \"raw_section_label\": \"乙、測驗題部分\", \"subject\": \"會計學概要\", \"year\": \"103\", \"exam_name\": \"103年專門建築師技師第二次食品技師考試不動產經紀人記帳士考試\", \"original_question_number\": 4, \"answer_corrected\": false, \"flags\": [], \"slug\": \"bookkeeper\", \"db_exam_id\": \"bookkeeper\"}'::jsonb, NULL),\n  ('bookkeeper-moex-01347', 'bookkeeper', 'bookkeeper-moex-103-d35177eb', 'sub-bookkeeper-01', NULL, 'single_choice', '企業有現金$30,000，應付票據$25,000，應付帳款$43,000，預收服務收入$70,000，租金支出$48,000， 根據上述資料，該企業之負債總額應為：', '[\"$98,000\", \"$55,000\", \"$138,000\", \"$68,000\"]'::jsonb, 2, NULL, TRUE, 'official', TRUE, 1, '{\"parser_version\": \"moex_license_v1.0\", \"parsed_at\": \"2026-04-25T04:29:27+00:00\", \"source_pdf_sha1\": \"eb7c2b3095ad\", \"answer_pdf_sha1\": \"151da49cfd80\", \"source_family\": \"moex-gov-tw\", \"moex\": {\"exam_code\": \"103170\", \"c\": \"602\", \"s\": \"1302\", \"q\": \"1\"}, \"raw_section_label\": \"乙、測驗題部分\", \"subject\": \"會計學概要\", \"year\": \"103\", \"exam_name\": \"103年專門建築師技師第二次食品技師考試不動產經紀人記帳士考試\", \"original_question_number\": 5, \"answer_corrected\": false, \"flags\": [], \"slug\": \"bookkeeper\", \"db_exam_id\": \"bookkeeper\"}'::jsonb, NULL),\n  ('bookkeeper-moex-01348', 'bookkeeper', 'bookkeeper-moex-103-d35177eb', 'sub-bookkeeper-01', NULL, 'single_choice', '開立遠期本票償還積欠的貨款，會使：', '[\"負債總額不變\", \"負債總額減少\", \"負債總額增加\", \"資產總額減少\"]'::jsonb, 0, NULL, TRUE, 'official', TRUE, 1, '{\"parser_version\": \"moex_license_v1.0\", \"parsed_at\": \"2026-04-25T04:29:27+00:00\", \"source_pdf_sha1\": \"eb7c2b3095ad\", \"answer_pdf_sha1\": \"151da49cfd80\", \"source_family\": \"moex-gov-tw\", \"moex\": {\"exam_code\": \"103170\", \"c\": \"602\", \"s\": \"1302\", \"q\": \"1\"}, \"raw_section_label\": \"乙、測驗題部分\", \"subject\": \"會計學概要\", \"year\": \"103\", \"exam_name\": \"103年專門建築師技師第二次食品技師考試不動產經紀人記帳士考試\", \"original_question_number\": 6, \"answer_corrected\": false, \"flags\": [], \"slug\": \"bookkeeper\", \"db_exam_id\": \"bookkeeper\"}'::jsonb, NULL),\n  ('bookkeeper-moex-01349', 'bookkeeper', 'bookkeeper-moex-103-d35177eb', 'sub-bookkeeper-01', NULL, 'single_choice', '期初存貨少計$2,000，期末存貨多計$5,000，將使本期淨利：', '[\"多計$3,000\", \"少計$3,000\", \"多計$7,000\", \"少計$7,000\"]'::jsonb, 2, NULL, TRUE, 'official', TRUE, 1, '{\"parser_version\": \"moex_license_v1.0\", \"parsed_at\": \"2026-04-25T04:29:27+00:00\", \"source_pdf_sha1\": \"eb7c2b3095ad\", \"answer_pdf_sha1\": \"151da49cfd80\", \"source_family\": \"moex-gov-tw\", \"moex\": {\"exam_code\": \"103170\", \"c\": \"602\", \"s\": \"1302\", \"q\": \"1\"}, \"raw_section_label\": \"乙、測驗題部分\", \"subject\": \"會計學概要\", \"year\": \"103\", \"exam_name\": \"103年專門建築師技師第二次食品技師考試不動產經紀人記帳士考試\", \"original_question_number\": 7, \"answer_corrected\": false, \"flags\": [], \"slug\": \"bookkeeper\", \"db_exam_id\": \"bookkeeper\"}'::jsonb, NULL),\n  ('bookkeeper-moex-01350', 'bookkeeper', 'bookkeeper-moex-103-d35177eb', 'sub-bookkeeper-01', NULL, 'single_choice', '股票股利將使：', '[\"資產及股東權益同時減少\", \"資產及股東權益同時增加\", \"資產減少及股東權益增加\", \"資產及股東權益不變\"]'::jsonb, 3, NULL, TRUE, 'official', TRUE, 1, '{\"parser_version\": \"moex_license_v1.0\", \"parsed_at\": \"2026-04-25T04:29:27+00:00\", \"source_pdf_sha1\": \"eb7c2b3095ad\", \"answer_pdf_sha1\": \"151da49cfd80\", \"source_family\": \"moex-gov-tw\", \"moex\": {\"exam_code\": \"103170\", \"c\": \"602\", \"s\": \"1302\", \"q\": \"1\"}, \"raw_section_label\": \"乙、測驗題部分\", \"subject\": \"會計學概要\", \"year\": \"103\", \"exam_name\": \"103年專門建築師技師第二次食品技師考試不動產經紀人記帳士考試\", \"original_question_number\": 8, \"answer_corrected\": false, \"flags\": [], \"slug\": \"bookkeeper\", \"db_exam_id\": \"bookkeeper\"}'::jsonb, NULL),\n  ('bookkeeper-moex-01351', 'bookkeeper', 'bookkeeper-moex-103-d35177eb', 'sub-bookkeeper-01', NULL, 'single_choice', '收得客戶11月16日出具面額$1,000，年利率6%，三個月到期之應收票據，在年底資產負債表上， 應報導：', '[\"應收票據$1,015\", \"應收票據$1,000及應收利息$15\", \"應收票據$1,000及應收利息$7.5\", \"應收票據$1,000及應收利息$10\"]'::jsonb, 2, NULL, TRUE, 'official', TRUE, 1, '{\"parser_version\": \"moex_license_v1.0\", \"parsed_at\": \"2026-04-25T04:29:27+00:00\", \"source_pdf_sha1\": \"eb7c2b3095ad\", \"answer_pdf_sha1\": \"151da49cfd80\", \"source_family\": \"moex-gov-tw\", \"moex\": {\"exam_code\": \"103170\", \"c\": \"602\", \"s\": \"1302\", \"q\": \"1\"}, \"raw_section_label\": \"乙、測驗題部分\", \"subject\": \"會計學概要\", \"year\": \"103\", \"exam_name\": \"103年專門建築師技師第二次食品技師考試不動產經紀人記帳士考試\", \"original_question_number\": 9, \"answer_corrected\": false, \"flags\": [], \"slug\": \"bookkeeper\", \"db_exam_id\": \"bookkeeper\"}'::jsonb, NULL)\nON CONFLICT (id) DO NOTHING;\n", "-- moex_license_ingest questions batch 63/330 (50 rows)\n\nINSERT INTO public.questions (id, exam_id, paper_id, subject_id, chapter_id, question_type, question_text, options, correct_answer, correct_answer_json, auto_gradable, source, is_active, version, source_meta, explanation)\nVALUES\n('bookkeeper-moex-01352', 'bookkeeper', 'bookkeeper-moex-103-d35177eb', 'sub-bookkeeper-01', NULL, 'single_choice', '甲公司成立於X1年初，近年存貨成本的資料如下：X1年底成本$151,000，淨變現價值$145,000；X2年 底成本$193,000，淨變現價值$190,000；X3年底成本$178,000，淨變現價值$179,000。另假設甲公司以備 抵存貨跌價損失科目記錄期末存貨之評價結果，則X3年底存貨評價分錄應借記：', '[\"備抵存貨跌價損失$3,000\", \"備抵存貨跌價損失$8,000\", \"備抵存貨跌價損失$9,000\", \"備抵存貨跌價損失$1,000\"]'::jsonb, 0, NULL, TRUE, 'official', TRUE, 1, '{\"parser_version\": \"moex_license_v1.0\", \"parsed_at\": \"2026-04-25T04:29:27+00:00\", \"source_pdf_sha1\": \"eb7c2b3095ad\", \"answer_pdf_sha1\": \"151da49cfd80\", \"source_family\": \"moex-gov-tw\", \"moex\": {\"exam_code\": \"103170\", \"c\": \"602\", \"s\": \"1302\", \"q\": \"1\"}, \"raw_section_label\": \"乙、測驗題部分\", \"subject\": \"會計學概要\", \"year\": \"103\", \"exam_name\": \"103年專門建築師技師第二次食品技師考試不動產經紀人記帳士考試\", \"original_question_number\": 10, \"answer_corrected\": false, \"flags\": [], \"slug\": \"bookkeeper\", \"db_exam_id\": \"bookkeeper\"}'::jsonb, NULL),\n  ('bookkeeper-moex-01353', 'bookkeeper', 'bookkeeper-moex-103-d35177eb', 'sub-bookkeeper-01', NULL, 'single_choice', '下列那一項會加強現金支出的控制：', '[\"所有的現金支出均由現金收入中支付\", \"不可由同一人掌管出納及編製銀行存款調節表\", \"現金支出之授權及出納由同一人擔任\", \"支票的準備與審核由同一人擔任\"]'::jsonb, 1, NULL, TRUE, 'official', TRUE, 1, '{\"parser_version\": \"moex_license_v1.0\", \"parsed_at\": \"2026-04-25T04:29:27+00:00\", \"source_pdf_sha1\": \"eb7c2b3095ad\", \"answer_pdf_sha1\": \"151da49cfd80\", \"source_family\": \"moex-gov-tw\", \"moex\": {\"exam_code\": \"103170\", \"c\": \"602\", \"s\": \"1302\", \"q\": \"1\"}, \"raw_section_label\": \"乙、測驗題部分\", \"subject\": \"會計學概要\", \"year\": \"103\", \"exam_name\": \"103年專門建築師技師第二次食品技師考試不動產經紀人記帳士考試\", \"original_question_number\": 11, \"answer_corrected\": false, \"flags\": [], \"slug\": \"bookkeeper\", \"db_exam_id\": \"bookkeeper\"}'::jsonb, NULL),\n  ('bookkeeper-moex-01354', 'bookkeeper', 'bookkeeper-moex-103-d35177eb', 'sub-bookkeeper-01', NULL, 'single_choice', '甲公司X1年1月1日備抵壞帳餘額為$14,000（貸餘），當年度沖銷壞帳為$6,000，收回沖銷的壞帳 為$2,000。根據以往經驗，期末應收帳款的 5%會成為壞帳，甲公司 X1 年 12 月 31 日的應收帳款為 $300,000。則X1年度的壞帳費用為：', '[\"$15,000\", \"$11,000\", \"$9,000\", \"$5,000\"]'::jsonb, 3, NULL, TRUE, 'official', TRUE, 1, '{\"parser_version\": \"moex_license_v1.0\", \"parsed_at\": \"2026-04-25T04:29:27+00:00\", \"source_pdf_sha1\": \"eb7c2b3095ad\", \"answer_pdf_sha1\": \"151da49cfd80\", \"source_family\": \"moex-gov-tw\", \"moex\": {\"exam_code\": \"103170\", \"c\": \"602\", \"s\": \"1302\", \"q\": \"1\"}, \"raw_section_label\": \"乙、測驗題部分\", \"subject\": \"會計學概要\", \"year\": \"103\", \"exam_name\": \"103年專門建築師技師第二次食品技師考試不動產經紀人記帳士考試\", \"original_question_number\": 12, \"answer_corrected\": false, \"flags\": [], \"slug\": \"bookkeeper\", \"db_exam_id\": \"bookkeeper\"}'::jsonb, NULL),\n  ('bookkeeper-moex-01355', 'bookkeeper', 'bookkeeper-moex-103-d35177eb', 'sub-bookkeeper-01', NULL, 'single_choice', '甲公司購置機器一部，買價$560,000，另付安裝費及試車費$60,000，採直線法折舊，估計可用 6 年，殘 值為$20,000，使用滿三年後，於第四年初發現機器僅能再用2年，且無殘值，則第四年終應計提折舊：', '[\"$100,000\", \"$130,000\", \"$150,000\", \"$160,000\"]'::jsonb, 3, NULL, TRUE, 'official', TRUE, 1, '{\"parser_version\": \"moex_license_v1.0\", \"parsed_at\": \"2026-04-25T04:29:27+00:00\", \"source_pdf_sha1\": \"eb7c2b3095ad\", \"answer_pdf_sha1\": \"151da49cfd80\", \"source_family\": \"moex-gov-tw\", \"moex\": {\"exam_code\": \"103170\", \"c\": \"602\", \"s\": \"1302\", \"q\": \"1\"}, \"raw_section_label\": \"乙、測驗題部分\", \"subject\": \"會計學概要\", \"year\": \"103\", \"exam_name\": \"103年專門建築師技師第二次食品技師考試不動產經紀人記帳士考試\", \"original_question_number\": 13, \"answer_corrected\": false, \"flags\": [], \"slug\": \"bookkeeper\", \"db_exam_id\": \"bookkeeper\"}'::jsonb, NULL),\n  ('bookkeeper-moex-01356', 'bookkeeper', 'bookkeeper-moex-103-d35177eb', 'sub-bookkeeper-01', NULL, 'single_choice', '甲公司從民國97年至99年間進行新產品的研發，於99年底時該專利產生之無形資產符合定義及認列條 件，在此之前，於97年至99年間每年花費$100,000。99年底向政府申請專利權另耗費$50,000，則專利 權無形資產之入帳成本為：', '[\"$50,000\", \"$150,000\", \"$300,000\", \"$350,000\"]'::jsonb, 0, NULL, TRUE, 'official', TRUE, 1, '{\"parser_version\": \"moex_license_v1.0\", \"parsed_at\": \"2026-04-25T04:29:27+00:00\", \"source_pdf_sha1\": \"eb7c2b3095ad\", \"answer_pdf_sha1\": \"151da49cfd80\", \"source_family\": \"moex-gov-tw\", \"moex\": {\"exam_code\": \"103170\", \"c\": \"602\", \"s\": \"1302\", \"q\": \"1\"}, \"raw_section_label\": \"乙、測驗題部分\", \"subject\": \"會計學概要\", \"year\": \"103\", \"exam_name\": \"103年專門建築師技師第二次食品技師考試不動產經紀人記帳士考試\", \"original_question_number\": 14, \"answer_corrected\": false, \"flags\": [], \"slug\": \"bookkeeper\", \"db_exam_id\": \"bookkeeper\"}'::jsonb, NULL),\n  ('bookkeeper-moex-01357', 'bookkeeper', 'bookkeeper-moex-103-d35177eb', 'sub-bookkeeper-01', NULL, 'single_choice', '稅前淨利$240,000，所得稅率25%，普通股在年初有100,000股，9月1日增資發行60,000股，則每股 盈餘為：', '[\"$1.50\", \"$2.00\", \"$2.40\", \"$4.00\"]'::jsonb, 0, NULL, TRUE, 'official', TRUE, 1, '{\"parser_version\": \"moex_license_v1.0\", \"parsed_at\": \"2026-04-25T04:29:27+00:00\", \"source_pdf_sha1\": \"eb7c2b3095ad\", \"answer_pdf_sha1\": \"151da49cfd80\", \"source_family\": \"moex-gov-tw\", \"moex\": {\"exam_code\": \"103170\", \"c\": \"602\", \"s\": \"1302\", \"q\": \"1\"}, \"raw_section_label\": \"乙、測驗題部分\", \"subject\": \"會計學概要\", \"year\": \"103\", \"exam_name\": \"103年專門建築師技師第二次食品技師考試不動產經紀人記帳士考試\", \"original_question_number\": 15, \"answer_corrected\": false, \"flags\": [], \"slug\": \"bookkeeper\", \"db_exam_id\": \"bookkeeper\"}'::jsonb, NULL),\n  ('bookkeeper-moex-01358', 'bookkeeper', 'bookkeeper-moex-103-d35177eb', 'sub-bookkeeper-01', NULL, 'single_choice', '甲公司生產聖誕飾品，本年度成本資料如下：直接材料$45,000，工廠水電費$23,000，直接人工$20,000， 銷售人員薪資$15,000，間接材料$10,000，辦公室租金$30,000，間接人工$8,000，下列敘述何者正確？', '[\"主要成本$83,000\", \"製造費用$71,000\", \"製造成本$106,000\", \"加工成本$91,000\"]'::jsonb, 2, NULL, TRUE, 'official', TRUE, 1, '{\"parser_version\": \"moex_license_v1.0\", \"parsed_at\": \"2026-04-25T04:29:27+00:00\", \"source_pdf_sha1\": \"eb7c2b3095ad\", \"answer_pdf_sha1\": \"151da49cfd80\", \"source_family\": \"moex-gov-tw\", \"moex\": {\"exam_code\": \"103170\", \"c\": \"602\", \"s\": \"1302\", \"q\": \"1\"}, \"raw_section_label\": \"乙、測驗題部分\", \"subject\": \"會計學概要\", \"year\": \"103\", \"exam_name\": \"103年專門建築師技師第二次食品技師考試不動產經紀人記帳士考試\", \"original_question_number\": 16, \"answer_corrected\": false, \"flags\": [], \"slug\": \"bookkeeper\", \"db_exam_id\": \"bookkeeper\"}'::jsonb, NULL),\n  ('bookkeeper-moex-01359', 'bookkeeper', 'bookkeeper-moex-103-d35177eb', 'sub-bookkeeper-01', NULL, 'single_choice', '甲公司報導年度淨利$85,000，當年度應收帳款餘額增加$7,000，應付帳款餘額減少$3,000，折舊費用為 $5,000。該公司當年度營業活動現金流入為：', '[\"$80,000\", \"$84,000\", \"$85,000\", \"$100,000\"]'::jsonb, 0, NULL, TRUE, 'official', TRUE, 1, '{\"parser_version\": \"moex_license_v1.0\", \"parsed_at\": \"2026-04-25T04:29:27+00:00\", \"source_pdf_sha1\": \"eb7c2b3095ad\", \"answer_pdf_sha1\": \"151da49cfd80\", \"source_family\": \"moex-gov-tw\", \"moex\": {\"exam_code\": \"103170\", \"c\": \"602\", \"s\": \"1302\", \"q\": \"1\"}, \"raw_section_label\": \"乙、測驗題部分\", \"subject\": \"會計學概要\", \"year\": \"103\", \"exam_name\": \"103年專門建築師技師第二次食品技師考試不動產經紀人記帳士考試\", \"original_question_number\": 17, \"answer_corrected\": false, \"flags\": [], \"slug\": \"bookkeeper\", \"db_exam_id\": \"bookkeeper\"}'::jsonb, NULL),\n  ('bookkeeper-moex-01360', 'bookkeeper', 'bookkeeper-moex-103-d35177eb', 'sub-bookkeeper-01', NULL, 'single_choice', '期初存貨$35,000，進貨淨額為$146,000，銷貨收入$240,000，銷貨退回與折讓$20,000，設平均毛利率30%， 試問採毛利法估計之期末存貨金額為：', '[\"$13,000\", \"$27,000\", \"$109,000\", \"$115,000\"]'::jsonb, 1, NULL, TRUE, 'official', TRUE, 1, '{\"parser_version\": \"moex_license_v1.0\", \"parsed_at\": \"2026-04-25T04:29:27+00:00\", \"source_pdf_sha1\": \"eb7c2b3095ad\", \"answer_pdf_sha1\": \"151da49cfd80\", \"source_family\": \"moex-gov-tw\", \"moex\": {\"exam_code\": \"103170\", \"c\": \"602\", \"s\": \"1302\", \"q\": \"1\"}, \"raw_section_label\": \"乙、測驗題部分\", \"subject\": \"會計學概要\", \"year\": \"103\", \"exam_name\": \"103年專門建築師技師第二次食品技師考試不動產經紀人記帳士考試\", \"original_question_number\": 18, \"answer_corrected\": false, \"flags\": [], \"slug\": \"bookkeeper\", \"db_exam_id\": \"bookkeeper\"}'::jsonb, NULL),\n  ('bookkeeper-moex-01361', 'bookkeeper', 'bookkeeper-moex-103-d35177eb', 'sub-bookkeeper-01', NULL, 'single_choice', '當公司買回庫藏股時，可能會造成：', '[\"資產增加，股東權益減少\", \"資產減少，股東權益增加\", \"資產與股東權益同時增加\", \"資產與股東權益同時減少\"]'::jsonb, 3, NULL, TRUE, 'official', TRUE, 1, '{\"parser_version\": \"moex_license_v1.0\", \"parsed_at\": \"2026-04-25T04:29:27+00:00\", \"source_pdf_sha1\": \"eb7c2b3095ad\", \"answer_pdf_sha1\": \"151da49cfd80\", \"source_family\": \"moex-gov-tw\", \"moex\": {\"exam_code\": \"103170\", \"c\": \"602\", \"s\": \"1302\", \"q\": \"1\"}, \"raw_section_label\": \"乙、測驗題部分\", \"subject\": \"會計學概要\", \"year\": \"103\", \"exam_name\": \"103年專門建築師技師第二次食品技師考試不動產經紀人記帳士考試\", \"original_question_number\": 19, \"answer_corrected\": false, \"flags\": [], \"slug\": \"bookkeeper\", \"db_exam_id\": \"bookkeeper\"}'::jsonb, NULL)\nON CONFLICT (id) DO NOTHING;\n"]}